MANIFEST.in
README.md
setup.py
assets/licht_icon.svg
assets/licht_icon_dark.svg
licht/__init__.py
licht/__main__.py
licht/app.py
licht/constants.py
licht/data.py
licht/parsing.py
licht/rest.py
licht/utils.py
licht.egg-info/PKG-INFO
licht.egg-info/SOURCES.txt
licht.egg-info/dependency_links.txt
licht.egg-info/entry_points.txt
licht.egg-info/requires.txt
licht.egg-info/top_level.txt